rna/__init__.py
rna/__main__.py
rna/config.py
rna/log.py
rna/parsing.py
rna/path.py
rna/pattern/__init__.py
rna/pattern/backend.py
rna/pattern/composite.py
rna/pattern/decorator.py
rna/pattern/link.py
rna/pattern/singleton.py
rna/pattern/strategy.py
rna/pattern/switch.py
rna/plotting/__init__.py
rna/plotting/backends/__init__.py
rna/plotting/backends/matplotlib.py
rna/plotting/backends/pyqtgraph.py
rna/plotting/base.py
rna/plotting/colors.py
rna/plotting/core.py
rna/plotting/mplstyles/rna.mplstyle
rna/plotting/mplstyles/tfields.mplstyle
rna/plotting/paths.py
rna/polymorphism.py
rna/process.py
rna-0.13.2.dist-info/AUTHORS.rst
rna-0.13.2.dist-info/LICENSE.rst
rna-0.13.2.dist-info/METADATA
rna-0.13.2.dist-info/WHEEL
rna-0.13.2.dist-info/RECORD
