Metadata-Version: 2.1
Name: rna
Version: 0.13.2
Summary: Basic and essential code building blocks of all pythons
Home-page: https://gitlab.mpcdf.mpg.de/dboe/rna
License: MIT
Keywords: plotting, matplotlib, pyqtgraph, backend, logging, path, argparse
Author: Daniel Böckenhoff
Author-email: dboe@ipp.mpg.de
Requires-Python: >=3.8,<4.0
Classifier: Development Status :: 3 - Alpha
Classifier: License :: OSI Approved :: MIT License
Classifier: Programming Language :: Python
Classifier: Programming Language :: Python :: 3
Classifier: Programming Language :: Python :: 3.8
Classifier: Programming Language :: Python :: 3.9
Classifier: Programming Language :: Python :: 3.10
Classifier: Programming Language :: Python :: 3.11
Classifier: Programming Language :: Python :: 3.12
Provides-Extra: categorical
Provides-Extra: config
Provides-Extra: pyqtgraph
Requires-Dist: hydra_core ; extra == "config"
Requires-Dist: matplotlib
Requires-Dist: numpy (>=1.22)
Requires-Dist: omegaconf ; extra == "config"
Requires-Dist: pathlib ; python_version < "3.10"
Requires-Dist: pyopengl ; extra == "pyqtgraph"
Requires-Dist: pyqt5 ; extra == "pyqtgraph"
Requires-Dist: pyqt5-qt5 (==5.15.2) ; extra == "pyqtgraph"
Requires-Dist: pyqtgraph ; extra == "pyqtgraph"
Requires-Dist: scikit-learn ; extra == "categorical"
Project-URL: Documentation, https://dboe.pages.mpcdf.de/rna
Project-URL: Repository, https://gitlab.mpcdf.mpg.de/dboe/rna
